[
    {
      "id": 1,
      "title": "Concerts and Music Festivals",
      "img": "https://i.ibb.co/BqgQ1Dt/Screenshot-83.png",
      "details": "A live music event featuring popular bands or artists. Consider genres like rock, pop, EDM, or classical, depending on your audience's taste.",
      "email": "musicconcert@example.com",
      "address": "123 Music St, Cityville",
      "location": "Megeve",
      "date": "2023-11-15",
      "price": "$100",
      "phone": "123-456-7890"
    },
    {
      "id": 2,
      "title": "Theater and Performing Arts",
      "img": "https://i.ibb.co/2KqJXd3/Screenshot-84.png",
      "details": "Organize a theatrical performance or a musical show. Choose a well-known play or musical that appeals to your audience.",
      "email": "theaterproduction@example.com",
      "address": "456 Theater Ave, Dramatown",
      "location": "Munich",
      "date": "2023-12-10",
      "price": "$70",
      "phone": "987-654-3210"
    },
    {
      "id": 3,
      "title": "Film Screenings and Premieres",
      "img": "https://i.ibb.co/Vj2qd4B/Screenshot-85.png",
      "details": "Arrange a screening of a popular film or series of movies, especially if your audience enjoys cinema.",
      "email": "filmscreening@example.com",
      "address": "789 Cinema Blvd, Movieville",
      "location": "Istanbul",
      "date": "2023-11-25",
      "price": " $25",
      "phone": "234-567-8901"
    },
    {
      "id": 4,
      "title": "Comedy Show or Stand-Up Performance",
      "img": "https://i.ibb.co/X80Bkn1/Screenshot-86.png",
      "details": "Invite comedians to perform a stand-up comedy show, providing laughter and entertainment for the audience.",
      "email": "comedyshow@example.com",
      "address": "321 Comedy Lane, Laughsville",
      "location": "Comedy Club",
      "date": "2023-12-05",
      "price": " $50",
      "phone": "876-543-2109"
    },
    {
      "id": 5,
      "title": "Sports Events",
      "img": "https://i.ibb.co/yyp3tfg/Screenshot-87.png",
      "details": "Arrange a dance performance, showcasing various dance styles such as contemporary, hip-hop, ballet, or cultural dances.",
      "email": "danceperformance@example.com",
      "address": "567 Dance Rd, Groovetown",
      "location": "Cape Town",
      "date": "2023-11-20",
      "price": "$60",
      "phone": "345-678-9012"
    },
    {
      "id": 6,
      "title": "Friendship Dinner",
      "img": "https://i.ibb.co/mcvsHjV/Screenshot-88.png",
      "details": "Host an interactive game night with trivia, board games, or video games. This can be a fun and engaging event for a diverse audience.",
      "email": "gamenight@example.com",
      "address": "789 Game Street, Playtown",
      "location": "Community Center",
      "date": "2023-12-18",
      "price": " $30",
      "phone": "234-567-8901"
    }
  ]